uscit.py
uscit-23.4.6.21.17.dist-info/LICENSE
uscit-23.4.6.21.17.dist-info/METADATA
uscit-23.4.6.21.17.dist-info/WHEEL
uscit-23.4.6.21.17.dist-info/top_level.txt
uscit-23.4.6.21.17.dist-info/RECORD
