Metadata-Version: 2.1
Name: uscit
Version: 23.4.6.21.17
Summary: simple package for very common functions
Author-email: diego aliaga <daliaga@chacaltaya.edu.bo>
Project-URL: Homepage, https://github.com/daliagachc/uscit
Project-URL: Bug Tracker, https://github.com/daliagachc/uscit/issues
Project-URL: Documentation, https://daliagachc.github.io/uscit/
Classifier: Programming Language :: Python :: 3
Classifier: License :: OSI Approved :: MIT License
Classifier: Operating System :: OS Independent
Requires-Python: >=3.7
License-File: LICENSE
